mod12counter_onFPGA/d_flip_flop.v
//d_flip_flop.sv file
//this module implements d flip flop using behavioural approach
module d_flip_flop(input d,input clk, input reset,output reg q, output reg qb);
always @(posedge clk or posedge reset)
    begin
        if (reset)
        begin
            q = 1'b0; 
            qb= 1'b1; 
        end
        else
        begin
            q=d; 
            qb=~q; 
        end
    end
endmodule

system_verilog_project_final/modulo12counter.sv
//modulo12counter.sv file
//this module implements modulo12counter using d flip flops using structural approach 
module modulo12counter(clk,reset,q); 
input clk,reset;
output [3:0]q;
wire [3:0]qb;
wire w1,w2,w3,w4,w5,w6,w7,w8,w9;
//according to circuit diagram
d_flip_flop dff0(qb[0],clk,reset,q[0],qb[0]);
xor x0(w1 ,q[0],q[1]);


d_flip_flop dff1(w1,clk,reset,q[1],qb[1]);

and a0(w2,q[2],qb[1]);
and a1(w3,q[2],qb[0]);
and a2(w4,qb[3],qb[2],q[1],q[0]);
or o1(w5,w2,w3,w4);

d_flip_flop dff2(w5,clk,reset,q[2],qb[2]);

and a3(w6,q[3],qb[1]);
and a4(w7,q[3],qb[0]);
and a5(w8,q[2],q[1],q[0]);
or o2(w9,w6,w7,w8);

d_flip_flop dff3(w9,clk,reset,q[3],qb[3]);

endmodule

system_verilog_project_final/countertb.sv
//countertb.sv file
// This module implements a modulo-12 counter testbench using OOP concept
module countertb;
import counter_pkg::*;
modulo12counter dut (.clk(clk), .reset(reset), .q(q));
// Declare inputs/outputs
reg clk, reset;
bit [3:0] temp;
wire [3:0] q;
Mod12Counter mod12counter_expected = new(clk, reset);
initial 
    begin 
        $dumpfile("countertb.vcd"); 
        $dumpvars(0, countertb);    
        clk <= 1'b0;      
        reset = 1'b1;     
        #5 $display(" Mod-12 Counter Output: %b, Expected Output: %b", q, mod12counter_expected.q);
        #8 reset = ~reset; 
        temp = 4'b0;     
        repeat(50) 
        begin   
            #5 clk = ~clk; 
        end
        $finish;           
    end
always @(posedge clk, posedge reset) begin
    verify(clk, reset);
end
// Task for verifying the counter output
task verify;
    input bit clk, reset;
    begin
        mod12counter_expected.update(reset);    
        mod12counter_expected.getOutput(temp);  
        temp = mod12counter_expected.q;        
        if (q== mod12counter_expected.q) begin        
        #5 $display(" Mod-12 Counter Output: %b, Expected Output: %b, Expected and Actual Output Matched", q, mod12counter_expected.q);
        end
        else
        begin
        #5 $display(" Mod-12 Counter Output: %b, Expected Output: %b, Expected and Actual Output did not match", q, mod12counter_expected.q);
        end
    end
endtask
endmodule

system_verilog_project_final/countertb.vcd
$date
	Fri Aug 04 12:54:29 2023
$end
$version
	Icarus Verilog
$end
$timescale
	1s
$end
$scope module countertb $end
$var wire 4 ! q [3:0] $end
$var reg 1 " clk $end
$var reg 1 # reset $end
$var reg 4 $ temp [3:0] $end
$scope module dut $end
$var wire 1 " clk $end
$var wire 1 # reset $end
$var wire 1 % w1 $end
$var wire 1 & w2 $end
$var wire 1 ' w3 $end
$var wire 1 ( w4 $end
$var wire 1 ) w5 $end
$var wire 1 * w6 $end
$var wire 1 + w7 $end
$var wire 1 , w8 $end
$var wire 1 - w9 $end
$var wire 4 . qb [3:0] $end
$var wire 4 / q [3:0] $end
$scope module dff0 $end
$var wire 1 " clk $end
$var wire 1 0 d $end
$var wire 1 # reset $end
$var reg 1 1 q $end
$var reg 1 2 qb $end
$upscope $end
$scope module dff1 $end
$var wire 1 " clk $end
$var wire 1 % d $end
$var wire 1 # reset $end
$var reg 1 3 q $end
$var reg 1 4 qb $end
$upscope $end
$scope module dff2 $end
$var wire 1 " clk $end
$var wire 1 ) d $end
$var wire 1 # reset $end
$var reg 1 5 q $end
$var reg 1 6 qb $end
$upscope $end
$scope module dff3 $end
$var wire 1 " clk $end
$var wire 1 - d $end
$var wire 1 # reset $end
$var reg 1 7 q $end
$var reg 1 8 qb $end
$upscope $end
$upscope $end
$scope task verify $end
$var reg 1 9 clk $end
$var reg 1 : reset $end
$upscope $end
$upscope $end
$enddefinitions $end
$comment Show the parameter values. $end
$dumpall
$end
#0
$dumpvars
0:
09
18
07
16
05
14
03
12
01
10
b0 /
b1111 .
0-
0,
0+
0*
0)
0(
0'
0&
0%
b0 $
1#
0"
b0 !
$end
#13
0#
#18
1%
00
b1 $
19
b1110 .
02
b1 !
b1 /
11
1"
#23
0"
#28
10
b10 $
12
01
b1101 .
04
b10 !
b10 /
13
1"
#33
0"
#38
1)
1(
0%
00
b11 $
b1100 .
02
b11 !
b11 /
11
1"
#43
0"
#48
0(
1'
1&
10
b100 $
12
01
14
03
b1011 .
06
b100 !
b100 /
15
1"
#53
0"
#58
0'
1%
00
b101 $
b1010 .
02
b101 !
b101 /
11
1"
#63
0"
#68
1'
0&
10
b110 $
12
01
b1001 .
04
b110 !
b110 /
13
1"
#73
0"
#78
0)
1-
0'
1,
0%
00
b111 $
b1000 .
02
b111 !
b111 /
11
1"
#83
0"
#88
0,
1+
1*
10
b1000 $
12
01
14
03
16
05
b111 .
08
b1000 !
b1000 /
17
1"
#93
0"
#98
0+
1%
00
b1001 $
b110 .
02
b1001 !
b1001 /
11
1"
#103
0"
#108
1+
0*
10
b1010 $
12
01
b101 .
04
b1010 !
b1010 /
13
1"
#113
0"
#118
0-
0+
0%
00
b1011 $
b100 .
02
b1011 !
b1011 /
11
1"
#123
0"
#128
10
b1100 $
12
01
14
03
b1111 .
18
b0 !
b0 /
07
1"
#133
0"
#138
1%
00
b1101 $
b1110 .
02
b1 !
b1 /
11
1"
#143
0"
#148
10
b1110 $
12
01
b1101 .
04
b10 !
b10 /
13
1"
#153
0"
#158
1)
1(
0%
00
b1111 $
b1100 .
02
b11 !
b11 /
11
1"
#163
0"
#168
0(
1'
1&
10
b0 $
12
01
14
03
b1011 .
06
b100 !
b100 /
15
1"
#173
0"
#178
0'
1%
00
b1 $
b1010 .
02
b101 !
b101 /
11
1"
#183
0"
#188
1'
0&
10
b10 $
12
01
b1001 .
04
b110 !
b110 /
13
1"
#193
0"
#198
0)
1-
0'
1,
0%
00
b11 $
b1000 .
02
b111 !
b111 /
11
1"
#203
0"
#208
0,
1+
1*
10
b100 $
12
01
14
03
16
05
b111 .
08
b1000 !
b1000 /
17
1"
#213
0"
#218
0+
1%
00
b101 $
b110 .
02
b1001 !
b1001 /
11
1"
#223
0"
#228
1+
0*
10
b110 $
12
01
b101 .
04
b1010 !
b1010 /
13
1"
#233
0"
#238
0-
0+
0%
00
b111 $
b100 .
02
b1011 !
b1011 /
11
1"
#243
0"
#248
10
b1000 $
12
01
14
03
b1111 .
18
b0 !
b0 /
07
1"
#253
0"
#258
1%
00
b1001 $
b1110 .
02
b1 !
b1 /
11
1"
